{
    "1": {
        "title": "Web",
        "description": "Need a website? We'll build one specific to your needs to increase sales, engagements, or aesthetic.",
        "img": "",
        "alt": ""
    },
    "2": {
        "title": "Identity",
        "description": "Are you trying to build a brand? Our artists will design a brand that speaks to your customers.",
        "img": "",
        "alt": ""
    },
    "3": {
        "title": "Learn",
        "description": "Want to connect with experts? We provide consultation services for web, design, business, tech, etc.",
        "img": "",
        "alt": ""
    }
}